faaspact_verifier/__init__.py
faaspact_verifier/context.py
faaspact_verifier/definitions.py
faaspact_verifier/exceptions.py
faaspact_verifier/py.typed
faaspact_verifier/types.py
faaspact_verifier/use_verifier.py
faaspact_verifier/abc/__init__.py
faaspact_verifier/abc/notification_gateway.py
faaspact_verifier/abc/pact_broker_gateway.py
faaspact_verifier/abc/verifier.py
faaspact_verifier/delivery/__init__.py
faaspact_verifier/delivery/cli.py
faaspact_verifier/delivery/github_prs.py
faaspact_verifier/delivery/github_prs_test.py
faaspact_verifier/entities/__init__.py
faaspact_verifier/entities/emulator.py
faaspact_verifier/entities/job.py
faaspact_verifier/gateways/__init__.py
faaspact_verifier/gateways/logger_notification_gateway.py
faaspact_verifier/gateways/pact_broker_gateway.py
faaspact_verifier/gateways/pactman_adapters.py
faaspact_verifier/gateways/pactman_verifier.py
faaspact_verifier/gateways/test_pactman_verifier.py
faaspact_verifier/user_defined/__init__.py
faaspact_verifier/user_defined/always.py
faaspact_verifier/user_defined/faasport.py
faaspact_verifier/user_defined/provider_state.py
faaspact_verifier-0.0.7.dist-info/LICENSE
faaspact_verifier-0.0.7.dist-info/METADATA
faaspact_verifier-0.0.7.dist-info/WHEEL
faaspact_verifier-0.0.7.dist-info/entry_points.txt
faaspact_verifier-0.0.7.dist-info/top_level.txt
faaspact_verifier-0.0.7.dist-info/RECORD
