Metadata-Version: 2.1
Name: faaspact-verifier
Version: 0.0.7
Summary: Verify pacts for python faas microservices.
Home-page: https://github.com/zhammer/faaspact-verifier
Author: Zach Hammer
Author-email: zach.the.hammer@gmail.com
License: MIT License
Platform: UNKNOWN
Requires-Dist: requests
Requires-Dist: pactman
Requires-Dist: colorama
